mur/__init__.py
mur/_mi.py
mur/_public.py
mur/_tools.py
mur/admin.py
mur/crypt.py
mur/user.py
py_gen_mur-1.1.5.dist-info/LICENSE.txt
py_gen_mur-1.1.5.dist-info/METADATA
py_gen_mur-1.1.5.dist-info/WHEEL
py_gen_mur-1.1.5.dist-info/entry_points.txt
py_gen_mur-1.1.5.dist-info/top_level.txt
py_gen_mur-1.1.5.dist-info/RECORD
