Metadata-Version: 2.1
Name: py-gen-mur
Version: 1.1.5
Summary: python generate machine_code, user_code, register_code
Home-page: https://github.com/lyy289065406/py-gen-mur
Author: EXP
Author-email: 289065406@qq.com
License: UNKNOWN
Project-URL: Bug Reports, https://github.com/lyy289065406/py-gen-mur/issues
Project-URL: Funding, https://github.com/lyy289065406/py-gen-mur/blob/master/imgs/donate-alipay.png
Project-URL: Say Thanks!, https://github.com/lyy289065406/py-gen-mur/blob/master/imgs/donate-wechat.png
Project-URL: Source, https://github.com/lyy289065406/py-gen-mur/
Keywords: machine,user,register
Platform: UNKNOWN
Classifier: Development Status :: 3 - Alpha
Classifier: Intended Audience :: Developers
Classifier: Topic :: Software Development :: Build Tools
Classifier: License :: OSI Approved :: MIT License
Classifier: Programming Language :: Python :: 3
Classifier: Programming Language :: Python :: 3.5
Classifier: Programming Language :: Python :: 3.6
Classifier: Programming Language :: Python :: 3.7
Classifier: Programming Language :: Python :: 3.8
Classifier: Programming Language :: Python :: 3 :: Only
Requires-Python: >=3.5, <4
License-File: LICENSE.txt
Requires-Dist: pyDes (>=2.0.1)
Requires-Dist: psutil (>=5.8.0)
Requires-Dist: pypiwin32
Requires-Dist: requests (>=2.22.0)
Provides-Extra: dev
Requires-Dist: check-manifest ; extra == 'dev'
Provides-Extra: test
Requires-Dist: coverage ; extra == 'test'
